shadertoy/__init__.py
shadertoy/shadertoy.py
shadertoy_api-1.0.2.dist-info/METADATA
shadertoy_api-1.0.2.dist-info/WHEEL
shadertoy_api-1.0.2.dist-info/top_level.txt
shadertoy_api-1.0.2.dist-info/RECORD
