Metadata-Version: 2.1
Name: shadertoy-api
Version: 1.0.2
Summary: A library for easily accessing the Shadertoy API.
Home-page: UNKNOWN
Author: Elijah Bevers
Author-email: pythontales@gmail.com
License: UNKNOWN
Platform: UNKNOWN
Classifier: Programming Language :: Python :: 3
Classifier: Topic :: Utilities
Classifier: Operating System :: OS Independent
Requires-Python: >=3.5
Requires-Dist: requests (>=2.25.1)
